pulumi_statsig/__init__.py
pulumi_statsig/_inputs.py
pulumi_statsig/_utilities.py
pulumi_statsig/entity_property.py
pulumi_statsig/experiment.py
pulumi_statsig/gate.py
pulumi_statsig/keys.py
pulumi_statsig/metric.py
pulumi_statsig/metric_source.py
pulumi_statsig/outputs.py
pulumi_statsig/provider.py
pulumi_statsig/pulumi-plugin.json
pulumi_statsig/py.typed
pulumi_statsig/config/__init__.py
pulumi_statsig/config/__init__.pyi
pulumi_statsig/config/vars.py
pulumi_statsig-0.0.1.dist-info/METADATA
pulumi_statsig-0.0.1.dist-info/WHEEL
pulumi_statsig-0.0.1.dist-info/top_level.txt
pulumi_statsig-0.0.1.dist-info/RECORD
