Metadata-Version: 2.4
Name: pulumi_statsig
Version: 0.0.1
Summary: A Pulumi package for creating and managing Statsig resources.
License: Apache-2.0
Project-URL: Homepage, https://www.statsig.com
Project-URL: Repository, https://github.com/statsig-io/pulumi-statsig
Keywords: statsig,category/cloud
Requires-Python: >=3.9
Requires-Dist: parver>=0.2.1
Requires-Dist: pulumi<4.0.0,>=3.165.0
Requires-Dist: semver>=2.8.1
Requires-Dist: typing-extensions<5,>=4.11; python_version < "3.11"
